MANIFEST.in
README.rst
requirements.txt
setup.py
django_tenant_templates/__init__.py
django_tenant_templates/loaders.py
django_tenant_templates/middleware.py
django_tenant_templates.egg-info/PKG-INFO
django_tenant_templates.egg-info/SOURCES.txt
django_tenant_templates.egg-info/dependency_links.txt
django_tenant_templates.egg-info/requires.txt
django_tenant_templates.egg-info/top_level.txt