Metadata-Version: 1.0
Name: django-tenant-templates
Version: 0.5
Summary: Tenant-aware templating for Django.
Home-page: https://github.com/grampajoe/django-tenant-templates
Author: Joe Friedl
Author-email: joe@joefriedl.net
License: MIT
Platform: UNKNOWN
